takao/__init__.py
takao/layout.html
takao/theme.toml
takao/partials/global-toc.jinja2
takao/partials/mobile-menubar.jinja2
takao/partials/page-nav.jinja2
takao/partials/prev-next.jinja2
takao/partials/readthedocs-menu.jinja2
takao/static/takao.css
takao/static/takao.js
takao/static/inter-ui/121b837e.woff2
takao/static/inter-ui/14c02214.woff2
takao/static/inter-ui/190ba617.woff2
takao/static/inter-ui/19cae34f.woff2
takao/static/inter-ui/1b6be3ff.woff2
takao/static/inter-ui/2bf75622.woff2
takao/static/inter-ui/390cd75a.woff2
takao/static/inter-ui/44f02707.woff2
takao/static/inter-ui/489746b9.woff2
takao/static/inter-ui/4a119645.woff2
takao/static/inter-ui/54fb5f2.woff2
takao/static/inter-ui/55132b46.woff2
takao/static/inter-ui/5feaed61.woff2
takao/static/inter-ui/61ea75a6.woff2
takao/static/inter-ui/647d26c.woff2
takao/static/inter-ui/65963639.woff2
takao/static/inter-ui/6a66e017.woff2
takao/static/inter-ui/6a93f17e.woff2
takao/static/inter-ui/6bb0fd00.woff2
takao/static/inter-ui/6c0194a2.woff2
takao/static/inter-ui/7aca0cc5.woff2
takao/static/inter-ui/8433fe73.woff2
takao/static/inter-ui/84774358.woff2
takao/static/inter-ui/LICENSE.txt
takao/static/inter-ui/a80b2975.woff2
takao/static/inter-ui/a886cf9b.woff2
takao/static/inter-ui/a891f617.woff2
takao/static/inter-ui/b29a61ff.woff2
takao/static/inter-ui/b3a5f48c.woff2
takao/static/inter-ui/bc73ee06.woff2
takao/static/inter-ui/c38c6d45.woff2
takao/static/inter-ui/c8d53904.woff2
takao/static/inter-ui/ce13c169.woff2
takao/static/inter-ui/ced51b6d.woff2
takao/static/inter-ui/d401a19a.woff2
takao/static/inter-ui/e2138ab8.woff2
takao/static/inter-ui/e318f796.woff2
takao/static/inter-ui/e98a2e6e.woff2
takao/static/inter-ui/ee5514c6.woff2
takao/static/inter-ui/f736ec65.woff2
takao/static/inter-ui/f7767345.woff2
takao-0.2.2.dist-info/METADATA
takao-0.2.2.dist-info/WHEEL
takao-0.2.2.dist-info/entry_points.txt
takao-0.2.2.dist-info/licenses/LICENCE
takao-0.2.2.dist-info/RECORD
