Metadata-Version: 2.4
Name: takao
Version: 0.2.2
Summary: A dark theme for Sphinx.
Project-URL: repository, https://github.com/reupen/takao.git
Project-URL: github, https://github.com/reupen/takao
Author: Reupen Shah
License-Expression: MIT
License-File: LICENCE
Requires-Python: >=3.11
Requires-Dist: sphinx>=4
